pyimage_scaler/__init__.py
pyimage_scaler/scaler.py
pyimage_scaler-1.1.2.dist-info/METADATA
pyimage_scaler-1.1.2.dist-info/WHEEL
pyimage_scaler-1.1.2.dist-info/top_level.txt
pyimage_scaler-1.1.2.dist-info/RECORD
