Metadata-Version: 2.4
Name: pyimage_scaler
Version: 1.1.2
Summary: A Python package to resize images (JPEG, PNG, BMP, GIF)
Author: codingmaster24
Requires-Python: >=3.7
Dynamic: author
Dynamic: description
Dynamic: description-content-type
Dynamic: requires-python
Dynamic: summary
